miyadaiku_theme_fontawesome/__init__.py
miyadaiku_theme_fontawesome/config.yml
miyadaiku_theme_fontawesome/externals/js/all.js
miyadaiku_theme_fontawesome/externals/js/all.min.js
miyadaiku_theme_fontawesome/externals/js/v4-shims.js
miyadaiku_theme_fontawesome/externals/js/v4-shims.min.js
miyadaiku_theme_fontawesome/templates/macros.html
miyadaiku_theme_fontawesome-1.1.0.dist-info/METADATA
miyadaiku_theme_fontawesome-1.1.0.dist-info/WHEEL
miyadaiku_theme_fontawesome-1.1.0.dist-info/top_level.txt
miyadaiku_theme_fontawesome-1.1.0.dist-info/RECORD
